odoo10_addon_base_search_custom_field_filter-10.0.1.0.1-nspkg.pth
odoo/addons/base_search_custom_field_filter/README.rst
odoo/addons/base_search_custom_field_filter/__init__.py
odoo/addons/base_search_custom_field_filter/__manifest__.py
odoo/addons/base_search_custom_field_filter/demo/demo_ir_ui_custom_field_filter.xml
odoo/addons/base_search_custom_field_filter/i18n/base_search_custom_field_filter.pot
odoo/addons/base_search_custom_field_filter/models/__init__.py
odoo/addons/base_search_custom_field_filter/models/base.py
odoo/addons/base_search_custom_field_filter/models/ir_ui_custom_field_filter.py
odoo/addons/base_search_custom_field_filter/readme/CONFIGURE.rst
odoo/addons/base_search_custom_field_filter/readme/CONTRIBUTORS.rst
odoo/addons/base_search_custom_field_filter/readme/DESCRIPTION.rst
odoo/addons/base_search_custom_field_filter/readme/USAGE.rst
odoo/addons/base_search_custom_field_filter/security/ir.model.access.csv
odoo/addons/base_search_custom_field_filter/static/description/icon.png
odoo/addons/base_search_custom_field_filter/static/description/index.html
odoo/addons/base_search_custom_field_filter/static/src/img/contact_search.png
odoo/addons/base_search_custom_field_filter/static/src/img/ir_ui_custom_field_filter.png
odoo/addons/base_search_custom_field_filter/static/src/js/search_input.js
odoo/addons/base_search_custom_field_filter/templates/assets.xml
odoo/addons/base_search_custom_field_filter/tests/__init__.py
odoo/addons/base_search_custom_field_filter/tests/test_search_custom_field.py
odoo/addons/base_search_custom_field_filter/views/ir_ui_custom_field_filter_views.xml
odoo10_addon_base_search_custom_field_filter-10.0.1.0.1.dist-info/METADATA
odoo10_addon_base_search_custom_field_filter-10.0.1.0.1.dist-info/WHEEL
odoo10_addon_base_search_custom_field_filter-10.0.1.0.1.dist-info/namespace_packages.txt
odoo10_addon_base_search_custom_field_filter-10.0.1.0.1.dist-info/top_level.txt
odoo10_addon_base_search_custom_field_filter-10.0.1.0.1.dist-info/RECORD
