Metadata-Version: 2.1
Name: odoo10-addon-base-search-custom-field-filter
Version: 10.0.1.0.1
Summary: Add custom filters for fields via UI
Home-page: https://github.com/OCA/server-ux
Author: Tecnativa, Odoo Community Association (OCA)
Author-email: support@odoo-community.org
License: AGPL-3
Platform: UNKNOWN
Classifier: Programming Language :: Python
Classifier: Framework :: Odoo
Classifier: License :: OSI Approved :: GNU Affero General Public License v3
Requires-Python: ~=2.7
Requires-Dist: odoo (<10.1dev,>=10.0)
